peewee_filters/__init__.py
peewee_filters/filters.py
peewee_filters/filterset.py
peewee_generic_filters-0.2.3.dist-info/LICENSE.md
peewee_generic_filters-0.2.3.dist-info/METADATA
peewee_generic_filters-0.2.3.dist-info/WHEEL
peewee_generic_filters-0.2.3.dist-info/top_level.txt
peewee_generic_filters-0.2.3.dist-info/RECORD
